ThaiPersonalCardExtract/__init__.py
ThaiPersonalCardExtract/utils.py
ThaiPersonalCardExtract/DrivingLicense/DrivingLicense.py
ThaiPersonalCardExtract/DrivingLicense/__init__.py
ThaiPersonalCardExtract/PersonalCard/PersonalCard.py
ThaiPersonalCardExtract/PersonalCard/__init__.py
ThaiPersonalCardExtract/ThaiGovernmentLottery/ThaiGovernmentLottery.py
ThaiPersonalCardExtract/ThaiGovernmentLottery/__init__.py
ThaiPersonalCardExtract/datasets/driving_license/config.json
ThaiPersonalCardExtract/datasets/driving_license/config.yaml
ThaiPersonalCardExtract/datasets/driving_license/thai-driving-license-template.jpg
ThaiPersonalCardExtract/datasets/identity_card/config.json
ThaiPersonalCardExtract/datasets/identity_card/config.yaml
ThaiPersonalCardExtract/datasets/identity_card/personal-card-back-template.jpg
ThaiPersonalCardExtract/datasets/identity_card/personal-card-back-template1.jpg
ThaiPersonalCardExtract/datasets/identity_card/personal-card-template.jpg
ThaiPersonalCardExtract/datasets/thai_government_lottery/config.json
ThaiPersonalCardExtract/datasets/thai_government_lottery/config.yaml
ThaiPersonalCardExtract/datasets/thai_government_lottery/thai-government-lottery-tamplate.jpg
thai_personal_card_extract-1.3.5.dist-info/LICENSE
thai_personal_card_extract-1.3.5.dist-info/METADATA
thai_personal_card_extract-1.3.5.dist-info/WHEEL
thai_personal_card_extract-1.3.5.dist-info/top_level.txt
thai_personal_card_extract-1.3.5.dist-info/RECORD
