Metadata-Version: 2.1
Name: thai-personal-card-extract
Version: 1.3.5
Summary: Library for extract infomation from thai personal identity card
Home-page: https://github.com/ggafiled/ThaiPersonalCardExtract
Author: ggafiled.io (Nattapol Krobklang)
Author-email: gafewkik234@gmail.com
License: Apache License 2.0
Download-URL: https://github.com/ggafiled/ThaiPersonalCardExtract.git
Project-URL: Bug Tracker, https://github.com/ggafiled/ThaiPersonalCardExtract/issues
Keywords: ocr optical character recognition deep learning neural network
Platform: UNKNOWN
Classifier: Development Status :: 5 - Production/Stable
Classifier: Topic :: Text Processing
Requires-Python: >=3.6
License-File: LICENSE
Requires-Dist: matplotlib
Requires-Dist: numpy
Requires-Dist: opencv-python (>=4.0)
Requires-Dist: Pillow (>=8.3)
Requires-Dist: pytesseract (>=0.3)
Requires-Dist: python-bidi
Requires-Dist: PyYAML
Requires-Dist: scikit-image
Requires-Dist: scipy
Requires-Dist: torch
Requires-Dist: torchvision (>=0.5)
Requires-Dist: easyocr
Requires-Dist: pylibdmtx
Requires-Dist: pylibdmtx[scripts]
